pithy/__init__.py
pithy/api.py
pithy/app.py
pithy/cfg.py
pithy/db.py
pithy/human_time.py
pithy/json_processor.py
pithy/thrift_client.py
pithy/utils.py
pithy/cli/__init__.py
pithy/cli/init.py
pithy/cli/utils.py
pithy/cli/templates/api/.gitignore.jinja
pithy/cli/templates/api/README.MD.jinja
pithy/cli/templates/api/cfg.yaml.jinja
pithy/cli/templates/api/requirements.txt.jinja
pithy/cli/templates/api/apis/__init__.py.jinja
pithy/cli/templates/api/apis/pithy_api.py.jinja
pithy/cli/templates/api/db/__init__.py.jinja
pithy/cli/templates/api/db/pithy_db.py.jinja
pithy/cli/templates/api/test_suites/__init__.py.jinja
pithy/cli/templates/api/test_suites/test_login.py.jinja
pithy/cli/templates/api/utils/__init__.py.jinja
pithy/cli/templates/app/.gitignore.jinja
pithy/cli/templates/app/README.MD.jinja
pithy/cli/templates/app/requirements.txt.jinja
pithy_test-0.0.20.dist-info/LICENSE
pithy_test-0.0.20.dist-info/METADATA
pithy_test-0.0.20.dist-info/WHEEL
pithy_test-0.0.20.dist-info/entry_points.txt
pithy_test-0.0.20.dist-info/top_level.txt
pithy_test-0.0.20.dist-info/RECORD
